gen3_tracker/__init__.py
gen3_tracker/cli.py
gen3_tracker/config.yaml
gen3_tracker/collaborator/__init__.py
gen3_tracker/collaborator/cli.py
gen3_tracker/collaborator/access/__init__.py
gen3_tracker/collaborator/access/cli.py
gen3_tracker/collaborator/access/requestor.py
gen3_tracker/collaborator/access/policies/__init__.py
gen3_tracker/collaborator/access/policies/add-project-default.yaml
gen3_tracker/collaborator/access/policies/add-user-read.yaml
gen3_tracker/collaborator/access/policies/add-user-write.yaml
gen3_tracker/common/__init__.py
gen3_tracker/config/__init__.py
gen3_tracker/gen3/__init__.py
gen3_tracker/gen3/indexd.py
gen3_tracker/gen3/jobs.py
gen3_tracker/gen3/buckets/__init__.py
gen3_tracker/gen3/buckets/cli.py
gen3_tracker/gen3/buckets/lister.py
gen3_tracker/git/__init__.py
gen3_tracker/git/adder.py
gen3_tracker/git/cli.py
gen3_tracker/git/cloner.py
gen3_tracker/git/initializer.py
gen3_tracker/git/snapshotter.py
gen3_tracker/meta/__init__.py
gen3_tracker/meta/cli.py
gen3_tracker/meta/dataframer.py
gen3_tracker/meta/entities.py
gen3_tracker/meta/skeleton.py
gen3_tracker/meta/validator.py
gen3_tracker/meta/visualizer.py
gen3_tracker/projects/__init__.py
gen3_tracker/projects/cli.py
gen3_tracker/projects/lister.py
gen3_tracker/projects/remover.py
gen3_tracker-0.0.7.dist-info/LICENSE
gen3_tracker-0.0.7.dist-info/METADATA
gen3_tracker-0.0.7.dist-info/WHEEL
gen3_tracker-0.0.7.dist-info/entry_points.txt
gen3_tracker-0.0.7.dist-info/top_level.txt
gen3_tracker-0.0.7.dist-info/RECORD
