Metadata-Version: 2.1
Name: gen3_tracker
Version: 0.0.7
Summary: A CLI for adding version control to Gen3 data submission projects.
Home-page: https://github.com/ACED-IDP/gen3_util
Author: walsbr
Author-email: walsbr@ohsu.edu
License-File: LICENSE
Requires-Dist: click
Requires-Dist: pytz
Requires-Dist: PyYAML
Requires-Dist: halo
Requires-Dist: tqdm
Requires-Dist: deepdiff
Requires-Dist: fhir.resources==7.1.0
Requires-Dist: orjson
Requires-Dist: nested-lookup
Requires-Dist: gen3
Requires-Dist: PyJWT==2.8.0
Requires-Dist: pydantic
Requires-Dist: requests
Requires-Dist: pandas
Requires-Dist: matplotlib==3.8.4
Requires-Dist: numpy
Requires-Dist: pyvis==0.3.2
Requires-Dist: ndjson
Requires-Dist: inflection
Requires-Dist: python-dateutil
Requires-Dist: deepmerge
Provides-Extra: dtale
Requires-Dist: dtale; extra == "dtale"
